{
  "appInfo" : {
    "build" : "233.14015.106",
    "buildDate" : "2024-01-25T05:01:00Z[UTC]",
    "productCode" : "IC",
    "generated" : "2024-01-27T11:02:03.5942991Z",
    "os" : "Windows 11.0",
    "runtime" : "JetBrains s.r.o. 17.0.9 17.0.9+7-b1087.11"
  },
  "runtimeInfo" : {
    "maxMemory" : 2147483648,
    "numberOfProcessors" : 8,
    "maxNumberOfIndexingThreads" : 7,
    "maxSizeOfFileForIntelliSense" : 2560000,
    "maxSizeOfFileForContentLoading" : 20971520
  },
  "type" : "Scanning",
  "projectIndexingActivityHistory" : {
    "projectName" : "springbootFirstAppApplication",
    "times" : {
      "scanningReason" : "On project open",
      "scanningType" : "FULL_ON_PROJECT_OPEN",
      "scanningId" : 0,
      "creatingIteratorsTime" : 139847000,
      "concurrentHandlingWallTimeWithoutPauses" : 7299950700,
      "concurrentHandlingWallTimeWithPauses" : 7299950700,
      "concurrentHandlingSumOfThreadTimesWithPauses" : 10407086200,
      "concurrentIterationAndScannersApplicationSumOfThreadTimesWithPauses" : 6466123700,
      "concurrentFileCheckSumOfThreadTimesWithPauses" : 3923828600,
      "delayedPushPropertiesStageTime" : 13501700,
      "indexExtensionsTime" : 9479100,
      "dumbModeStart" : "2024-01-27T11:01:56.0697772Z",
      "dumbWallTimeWithPauses" : 7514906900,
      "dumbWallTimeWithoutPauses" : 7514906900,
      "updatingStart" : "2024-01-27T11:01:56.0421635Z",
      "updatingEnd" : "2024-01-27T11:02:03.5846841Z",
      "totalWallTimeWithPauses" : 7542507400,
      "wallTimeOnPause" : 0,
      "wasInterrupted" : false,
      "totalWallTimeWithoutPauses" : 7542507400
    },
    "fileCount" : {
      "numberOfFileProviders" : 8,
      "numberOfScannedFiles" : 100692,
      "numberOfFilesIndexedByInfrastructureExtensionsDuringScan" : 0,
      "numberOfFilesScheduledForIndexingAfterScan" : 107
    },
    "scanningStatistics" : [ {
      "providerName" : "Module 'Hemanth' (all roots)",
      "numberOfScannedFiles" : 57276,
      "numberOfSkippedFiles" : 1,
      "numberOfFilesForIndexing" : 107,
      "numberOfFilesFullyIndexedByInfrastructureExtensions" : 0,
      "filesFullyIndexedByInfrastructureExtensions" : [ ],
      "statusTime" : 722705300,
      "totalOneThreadTimeWithPauses" : 7258222100,
      "iterationAndScannersApplicationTime" : 4703292000,
      "filesCheckTime" : 2550948800,
      "timeProcessingUpToDateFiles" : 2075900,
      "timeUpdatingContentLessIndexes" : 51846100,
      "timeIndexingWithoutContentViaInfrastructureExtension" : 9479100,
      "roots" : [ ]
    }, {
      "providerName" : "JDK 1.8 C:/Program Files/Java/jdk1.8.0_202",
      "numberOfScannedFiles" : 43194,
      "numberOfSkippedFiles" : 0,
      "numberOfFilesForIndexing" : 0,
      "numberOfFilesFullyIndexedByInfrastructureExtensions" : 0,
      "filesFullyIndexedByInfrastructureExtensions" : [ ],
      "statusTime" : 646156000,
      "totalOneThreadTimeWithPauses" : 2879713500,
      "iterationAndScannersApplicationTime" : 1714780700,
      "filesCheckTime" : 1164747300,
      "timeProcessingUpToDateFiles" : 0,
      "timeUpdatingContentLessIndexes" : 0,
      "timeIndexingWithoutContentViaInfrastructureExtension" : 0,
      "roots" : [ ]
    }, {
      "providerName" : "Indexable set contributor 'com.intellij.javaee.ExternalResourcesRootsProvider@6eb28795' (non-project)",
      "numberOfScannedFiles" : 215,
      "numberOfSkippedFiles" : 4,
      "numberOfFilesForIndexing" : 0,
      "numberOfFilesFullyIndexedByInfrastructureExtensions" : 0,
      "filesFullyIndexedByInfrastructureExtensions" : [ ],
      "statusTime" : 152605000,
      "totalOneThreadTimeWithPauses" : 185571900,
      "iterationAndScannersApplicationTime" : 17137400,
      "filesCheckTime" : 166415000,
      "timeProcessingUpToDateFiles" : 1996100,
      "timeUpdatingContentLessIndexes" : 0,
      "timeIndexingWithoutContentViaInfrastructureExtension" : 0,
      "roots" : [ ]
    }, {
      "providerName" : "Indexable set contributor 'org.jetbrains.kotlin.idea.base.indices.contributors.BuiltInsIndexableSetContributor@3276337c' (non-project)",
      "numberOfScannedFiles" : 7,
      "numberOfSkippedFiles" : 0,
      "numberOfFilesForIndexing" : 0,
      "numberOfFilesFullyIndexedByInfrastructureExtensions" : 0,
      "filesFullyIndexedByInfrastructureExtensions" : [ ],
      "statusTime" : 5611300,
      "totalOneThreadTimeWithPauses" : 21223600,
      "iterationAndScannersApplicationTime" : 8521000,
      "filesCheckTime" : 11067900,
      "timeProcessingUpToDateFiles" : 0,
      "timeUpdatingContentLessIndexes" : 0,
      "timeIndexingWithoutContentViaInfrastructureExtension" : 0,
      "roots" : [ ]
    }, {
      "providerName" : "Indexable set contributor 'Scratches & Consoles' (non-project)",
      "numberOfScannedFiles" : 0,
      "numberOfSkippedFiles" : 0,
      "numberOfFilesForIndexing" : 0,
      "numberOfFilesFullyIndexedByInfrastructureExtensions" : 0,
      "filesFullyIndexedByInfrastructureExtensions" : [ ],
      "statusTime" : 0,
      "totalOneThreadTimeWithPauses" : 15839900,
      "iterationAndScannersApplicationTime" : 5361500,
      "filesCheckTime" : 7958800,
      "timeProcessingUpToDateFiles" : 0,
      "timeUpdatingContentLessIndexes" : 0,
      "timeIndexingWithoutContentViaInfrastructureExtension" : 0,
      "roots" : [ ]
    }, {
      "providerName" : "Indexable set contributor 'Scratches & Consoles' (project)",
      "numberOfScannedFiles" : 0,
      "numberOfSkippedFiles" : 0,
      "numberOfFilesForIndexing" : 0,
      "numberOfFilesFullyIndexedByInfrastructureExtensions" : 0,
      "filesFullyIndexedByInfrastructureExtensions" : [ ],
      "statusTime" : 0,
      "totalOneThreadTimeWithPauses" : 15795900,
      "iterationAndScannersApplicationTime" : 5959500,
      "filesCheckTime" : 7251400,
      "timeProcessingUpToDateFiles" : 0,
      "timeUpdatingContentLessIndexes" : 0,
      "timeIndexingWithoutContentViaInfrastructureExtension" : 0,
      "roots" : [ ]
    }, {
      "providerName" : "Indexable set contributor 'com.intellij.javaee.ExternalResourcesRootsProvider@6eb28795' (project)",
      "numberOfScannedFiles" : 0,
      "numberOfSkippedFiles" : 0,
      "numberOfFilesForIndexing" : 0,
      "numberOfFilesFullyIndexedByInfrastructureExtensions" : 0,
      "filesFullyIndexedByInfrastructureExtensions" : [ ],
      "statusTime" : 0,
      "totalOneThreadTimeWithPauses" : 15485700,
      "iterationAndScannersApplicationTime" : 5625300,
      "filesCheckTime" : 7582600,
      "timeProcessingUpToDateFiles" : 0,
      "timeUpdatingContentLessIndexes" : 0,
      "timeIndexingWithoutContentViaInfrastructureExtension" : 0,
      "roots" : [ ]
    }, {
      "providerName" : "Indexable set contributor 'org.jetbrains.kotlin.idea.base.indices.contributors.BuiltInsIndexableSetContributor@3276337c' (project)",
      "numberOfScannedFiles" : 0,
      "numberOfSkippedFiles" : 0,
      "numberOfFilesForIndexing" : 0,
      "numberOfFilesFullyIndexedByInfrastructureExtensions" : 0,
      "filesFullyIndexedByInfrastructureExtensions" : [ ],
      "statusTime" : 0,
      "totalOneThreadTimeWithPauses" : 15233600,
      "iterationAndScannersApplicationTime" : 5446300,
      "filesCheckTime" : 7856800,
      "timeProcessingUpToDateFiles" : 0,
      "timeUpdatingContentLessIndexes" : 0,
      "timeIndexingWithoutContentViaInfrastructureExtension" : 0,
      "roots" : [ ]
    } ]
  }
}